setup.py
yify/__init__.py
yify_sub.egg-info/PKG-INFO
yify_sub.egg-info/SOURCES.txt
yify_sub.egg-info/dependency_links.txt
yify_sub.egg-info/entry_points.txt
yify_sub.egg-info/requires.txt
yify_sub.egg-info/top_level.txt