Metadata-Version: 1.0
Name: yify-sub
Version: 0.1.0
Summary: Download yify subtitle using only one command.
Home-page: UNKNOWN
Author: David
Author-email: UNKNOWN
License: MIT
Platform: UNKNOWN
